ml_insights/CVModel.py
ml_insights/__init__.py
ml_insights/calibration.py
ml_insights/cross_validation.py
ml_insights/insights.py
ml_insights/modeling_utils.py
ml_insights/shap_insights.py
ml_insights/utils.py
ml_insights-1.1.0.dist-info/licenses/LICENSE
ml_insights-1.1.0.dist-info/METADATA
ml_insights-1.1.0.dist-info/WHEEL
ml_insights-1.1.0.dist-info/top_level.txt
ml_insights-1.1.0.dist-info/RECORD
