Metadata-Version: 2.4
Name: ml_insights
Version: 1.1.0
Summary: Package to calibrate and understand ML Models
Author-email: Brian Lucena / Ramesh Sampath <brian@numeristical.com>
License-Expression: MIT
Project-URL: Homepage, https://github.com/numeristical/introspective
Project-URL: Issues, https://github.com/numeristical/introspective/issues
Classifier: Programming Language :: Python :: 3
Classifier: Operating System :: OS Independent
Requires-Python: >=3.8
License-File: LICENSE
Requires-Dist: pandas>=0.23
Requires-Dist: numpy>=1.23.5
Requires-Dist: matplotlib>=2.0.0
Requires-Dist: scikit-learn>=0.24.2
Requires-Dist: scipy>=1.6.0
Requires-Dist: splinecalib>=0.0.13
Dynamic: license-file
